[
 {
  "id_dep": 16,
  "departamento": "Alta Verapaz",
  "id_municipal": 1614,
  "municipio": "Chahal",
  "aip2019": 37.5,
  "aip2017": 50,
  "aip2015": 38.5,
  "aip2015insitu": 72.18,
  "aipPromedio": 42
 },
 {
  "id_dep": 16,
  "departamento": "Alta Verapaz",
  "id_municipal": 1613,
  "municipio": "Chisec",
  "aip2019": 72.5,
  "aip2017": 81.25,
  "aip2015": 0,
  "aip2015insitu": 6.67,
  "aipPromedio": 51.25
 },
 {
  "id_dep": 16,
  "departamento": "Alta Verapaz",
  "id_municipal": 1601,
  "municipio": "Cobán",
  "aip2019": 60,
  "aip2017": 0,
  "aip2015": 0,
  "aip2015insitu": 88.64,
  "aipPromedio": 20
 },
 {
  "id_dep": 16,
  "departamento": "Alta Verapaz",
  "id_municipal": 1615,
  "municipio": "Fray Bartolomé de las Casas",
  "aip2019": 91.25,
  "aip2017": 57.14,
  "aip2015": 64.81,
  "aip2015insitu": 87.67,
  "aipPromedio": 71.06666667
 },
 {
  "id_dep": 16,
  "departamento": "Alta Verapaz",
  "id_municipal": 1607,
  "municipio": "Panzós",
  "aip2019": 83.75,
  "aip2017": 0,
  "aip2015": 0,
  "aip2015insitu": 6.82,
  "aipPromedio": 27.91666667
 },
 {
  "id_dep": 16,
  "departamento": "Alta Verapaz",
  "id_municipal": 1617,
  "municipio": "Raxruhá",
  "aip2019": 68.42,
  "aip2017": 25,
  "aip2015": 19.38,
  "aip2015insitu": 69.42,
  "aipPromedio": 37.6
 },
 {
  "id_dep": 16,
  "departamento": "Alta Verapaz",
  "id_municipal": 1611,
  "municipio": "San Agustín Lanquín",
  "aip2019": 65,
  "aip2017": 78.57,
  "aip2015": 0,
  "aip2015insitu": 55.45,
  "aipPromedio": 47.85666667
 },
 {
  "id_dep": 16,
  "departamento": "Alta Verapaz",
  "id_municipal": 1608,
  "municipio": "Senahú",
  "aip2019": 78.75,
  "aip2017": 0,
  "aipPromedio": 39.375
 },
 {
  "id_dep": 16,
  "departamento": "Alta Verapaz",
  "id_municipal": 1603,
  "municipio": "San Cristóbal Verapaz",
  "aip2019": 61.25000000000001,
  "aip2017": 0,
  "aipPromedio": 30.625
 },
 {
  "id_dep": 16,
  "departamento": "Alta Verapaz",
  "id_municipal": 1610,
  "municipio": "San Juan Chamelco",
  "aip2019": 78.75,
  "aip2017": 0,
  "aip2015": 0,
  "aip2015insitu": 64.18,
  "aipPromedio": 26.25
 },
 {
  "id_dep": 16,
  "departamento": "Alta Verapaz",
  "id_municipal": 1606,
  "municipio": "San Miguel Tucurú",
  "aip2019": 47.5,
  "aip2017": 57.14,
  "aipPromedio": 52.32
 },
 {
  "id_dep": 16,
  "departamento": "Alta Verapaz",
  "id_municipal": 1609,
  "municipio": "San Pedro Carchá",
  "aip2019": 30,
  "aip2017": 55,
  "aip2015": 41.02,
  "aip2015insitu": 77.62,
  "aipPromedio": 42.00666667
 },
 {
  "id_dep": 16,
  "departamento": "Alta Verapaz",
  "id_municipal": 1616,
  "municipio": "Santa Catalina La Tinta",
  "aip2019": 34.21,
  "aip2017": 33.33,
  "aip2015": 0,
  "aip2015insitu": 45.83,
  "aipPromedio": 22.51333333
 },
 {
  "id_dep": 16,
  "departamento": "Alta Verapaz",
  "id_municipal": 1602,
  "municipio": "Santa Cruz Verapaz",
  "aip2019": 80,
  "aip2017": 20,
  "aip2015": 7.5,
  "aip2015insitu": 75.54,
  "aipPromedio": 35.83333333
 },
 {
  "id_dep": 16,
  "departamento": "Alta Verapaz",
  "id_municipal": 1612,
  "municipio": "Santa María Cahabón",
  "aip2019": 88.75,
  "aip2017": 0,
  "aipPromedio": 44.375
 },
 {
  "id_dep": 16,
  "departamento": "Alta Verapaz",
  "id_municipal": 1604,
  "municipio": "Tactic",
  "aip2019": 93.75,
  "aip2017": 25,
  "aip2015": 64.48,
  "aip2015insitu": 81.5,
  "aipPromedio": 61.07666667
 },
 {
  "id_dep": 16,
  "departamento": "Alta Verapaz",
  "id_municipal": 1605,
  "municipio": "Tamahú",
  "aip2019": 90,
  "aip2017": 30,
  "aipPromedio": 60
 },
 {
  "id_dep": 15,
  "departamento": "Baja Verapaz",
  "id_municipal": 1504,
  "municipio": "Cubulco",
  "aip2019": 86.36,
  "aip2017": 0,
  "aip2015": 0,
  "aip2015insitu": 88.52,
  "aipPromedio": 28.78666667
 },
 {
  "id_dep": 15,
  "departamento": "Baja Verapaz",
  "id_municipal": 1505,
  "municipio": "Granados",
  "aip2019": 85.71,
  "aip2017": 0,
  "aip2015": 0,
  "aip2015insitu": 78.07,
  "aipPromedio": 28.57
 },
 {
  "id_dep": 15,
  "departamento": "Baja Verapaz",
  "id_municipal": 1508,
  "municipio": "Purulhá",
  "aip2019": 72.72999999999999,
  "aip2017": 0,
  "aipPromedio": 36.365
 },
 {
  "id_dep": 15,
  "departamento": "Baja Verapaz",
  "id_municipal": 1503,
  "municipio": "Rabinal",
  "aip2019": 54.05,
  "aip2017": 0,
  "aipPromedio": 27.025
 },
 {
  "id_dep": 15,
  "departamento": "Baja Verapaz",
  "id_municipal": 1501,
  "municipio": "Salamá",
  "aip2019": 82.26,
  "aip2017": 0,
  "aipPromedio": 41.13
 },
 {
  "id_dep": 15,
  "departamento": "Baja Verapaz",
  "id_municipal": 1507,
  "municipio": "San Jerónimo",
  "aip2019": 74.19,
  "aip2017": 64.29,
  "aip2015": 0,
  "aip2015insitu": 72.7,
  "aipPromedio": 46.16
 },
 {
  "id_dep": 15,
  "departamento": "Baja Verapaz",
  "id_municipal": 1502,
  "municipio": "San Miguel Chicaj",
  "aip2019": 26.39,
  "aip2017": 0,
  "aip2015": 0,
  "aip2015insitu": 75.91,
  "aipPromedio": 8.796666667
 },
 {
  "id_dep": 15,
  "departamento": "Baja Verapaz",
  "id_municipal": 1506,
  "municipio": "Santa Cruz El Chol",
  "aip2019": 82.12,
  "aip2017": 85.71,
  "aip2015": 26.44,
  "aip2015insitu": 75.89,
  "aipPromedio": 64.75666667
 },
 {
  "id_dep": 4,
  "departamento": "Chimaltenango",
  "id_municipal": 411,
  "municipio": "Acatenango",
  "aip2019": 12.5,
  "aip2017": 5,
  "aip2015": 2.5,
  "aip2015insitu": 53.45,
  "aipPromedio": 6.666666667
 },
 {
  "id_dep": 4,
  "departamento": "Chimaltenango",
  "id_municipal": 401,
  "municipio": "Chimaltenango",
  "aip2019": 8.110000000000001,
  "aip2017": 28.57,
  "aipPromedio": 18.34
 },
 {
  "id_dep": 4,
  "departamento": "Chimaltenango",
  "id_municipal": 416,
  "municipio": "El Tejar",
  "aip2019": 25,
  "aip2017": 0,
  "aipPromedio": 12.5
 },
 {
  "id_dep": 4,
  "departamento": "Chimaltenango",
  "id_municipal": 414,
  "municipio": "Parramos",
  "aip2019": 21.21,
  "aip2017": 5,
  "aip2015": 0,
  "aip2015insitu": 69.73,
  "aipPromedio": 8.736666667
 },
 {
  "id_dep": 4,
  "departamento": "Chimaltenango",
  "id_municipal": 409,
  "municipio": "Patzicía",
  "aip2019": 38.16,
  "aip2017": 25,
  "aip2015": 0,
  "aip2015insitu": 16.98,
  "aipPromedio": 21.05333333
 },
 {
  "id_dep": 4,
  "departamento": "Chimaltenango",
  "id_municipal": 407,
  "municipio": "Patzún",
  "aip2019": 0,
  "aip2017": 0,
  "aipPromedio": 0
 },
 {
  "id_dep": 4,
  "departamento": "Chimaltenango",
  "id_municipal": 413,
  "municipio": "San Andrés Itzapa",
  "aip2019": 13.51,
  "aip2017": 0,
  "aip2015": 0,
  "aip2015insitu": 41.48,
  "aipPromedio": 4.503333333
 },
 {
  "id_dep": 4,
  "departamento": "Chimaltenango",
  "id_municipal": 402,
  "municipio": "San José Poaquil",
  "aip2019": 5.26,
  "aip2017": 0,
  "aipPromedio": 2.63
 },
 {
  "id_dep": 4,
  "departamento": "Chimaltenango",
  "id_municipal": 404,
  "municipio": "San Juan Comalapa",
  "aip2019": 0,
  "aip2017": 0,
  "aipPromedio": 0
 },
 {
  "id_dep": 4,
  "departamento": "Chimaltenango",
  "id_municipal": 403,
  "municipio": "San Martín Jilotepeque",
  "aip2019": 33.78,
  "aip2017": 25,
  "aip2015": 0,
  "aip2015insitu": 80.83,
  "aipPromedio": 19.59333333
 },
 {
  "id_dep": 4,
  "departamento": "Chimaltenango",
  "id_municipal": 408,
  "municipio": "San Miguel Pochuta",
  "aip2019": 0,
  "aip2017": 0,
  "aip2015": 0,
  "aip2015insitu": 79.88,
  "aipPromedio": 0
 },
 {
  "id_dep": 4,
  "departamento": "Chimaltenango",
  "id_municipal": 412,
  "municipio": "San Pedro Yepocapa",
  "aip2019": 14.47,
  "aip2017": 0,
  "aip2015": 0,
  "aip2015insitu": 28.78,
  "aipPromedio": 4.823333333
 },
 {
  "id_dep": 4,
  "departamento": "Chimaltenango",
  "id_municipal": 405,
  "municipio": "Santa Apolonia",
  "aip2019": 11.84,
  "aip2017": 0,
  "aipPromedio": 5.92
 },
 {
  "id_dep": 4,
  "departamento": "Chimaltenango",
  "id_municipal": 410,
  "municipio": "Santa Cruz Balanyá",
  "aip2019": 5.41,
  "aip2017": 0,
  "aipPromedio": 2.705
 },
 {
  "id_dep": 4,
  "departamento": "Chimaltenango",
  "id_municipal": 406,
  "municipio": "Tecpán Guatemala",
  "aip2019": 28.95,
  "aip2017": 0,
  "aipPromedio": 14.475
 },
 {
  "id_dep": 4,
  "departamento": "Chimaltenango",
  "id_municipal": 415,
  "municipio": "Zaragoza",
  "aip2019": 68.42,
  "aip2017": 33.33,
  "aip2015": 0,
  "aip2015insitu": 70.22,
  "aipPromedio": 33.91666667
 },
 {
  "id_dep": 20,
  "departamento": "Chiquimula",
  "id_municipal": 2005,
  "municipio": "Camotán",
  "aip2019": 6.25,
  "aip2017": 0,
  "aip2015": 0,
  "aip2015insitu": 73.86,
  "aipPromedio": 2.083333333
 },
 {
  "id_dep": 20,
  "departamento": "Chiquimula",
  "id_municipal": 2001,
  "municipio": "Chiquimula",
  "aip2019": 44.12,
  "aip2017": 25,
  "aip2015": 0,
  "aip2015insitu": 64.47,
  "aipPromedio": 23.04
 },
 {
  "id_dep": 20,
  "departamento": "Chiquimula",
  "id_municipal": 2008,
  "municipio": "Concepción las Minas",
  "aip2019": 51.32,
  "aip2017": 0,
  "aipPromedio": 25.66
 },
 {
  "id_dep": 20,
  "departamento": "Chiquimula",
  "id_municipal": 2007,
  "municipio": "Esquipulas",
  "aip2019": 60.529999999999994,
  "aip2017": 59.52,
  "aipPromedio": 60.025
 },
 {
  "id_dep": 20,
  "departamento": "Chiquimula",
  "id_municipal": 2011,
  "municipio": "Ipala",
  "aip2019": 38.16,
  "aip2017": 68.75,
  "aipPromedio": 53.455
 },
 {
  "id_dep": 20,
  "departamento": "Chiquimula",
  "id_municipal": 2004,
  "municipio": "Jocotán",
  "aip2019": 61.84,
  "aip2017": 0,
  "aipPromedio": 30.92
 },
 {
  "id_dep": 20,
  "departamento": "Chiquimula",
  "id_municipal": 2006,
  "municipio": "Olopa",
  "aip2019": 47.14,
  "aip2017": 0,
  "aip2015": 0,
  "aip2015insitu": 53.49,
  "aipPromedio": 15.71333333
 },
 {
  "id_dep": 20,
  "departamento": "Chiquimula",
  "id_municipal": 2009,
  "municipio": "Quezaltepeque",
  "aip2019": 71.05,
  "aip2017": 43.75,
  "aipPromedio": 57.4
 },
 {
  "id_dep": 20,
  "departamento": "Chiquimula",
  "id_municipal": 2010,
  "municipio": "San Jacinto",
  "aip2019": 23.68,
  "aip2017": 0,
  "aip2015": 20.27,
  "aip2015insitu": 50,
  "aipPromedio": 14.65
 },
 {
  "id_dep": 20,
  "departamento": "Chiquimula",
  "id_municipal": 2002,
  "municipio": "San José La Arada",
  "aip2019": 44.74,
  "aip2017": 0,
  "aip2015": 6.25,
  "aip2015insitu": 85.42,
  "aipPromedio": 16.99666667
 },
 {
  "id_dep": 20,
  "departamento": "Chiquimula",
  "id_municipal": 2003,
  "municipio": "San Juan Ermita",
  "aip2019": 82,
  "aip2017": 25,
  "aip2015": 0,
  "aip2015insitu": 79.48,
  "aipPromedio": 35.66666667
 },
 {
  "id_dep": 2,
  "departamento": "El Progreso",
  "id_municipal": 205,
  "municipio": "El Jícaro",
  "aip2019": 51.970000000000006,
  "aip2017": 0,
  "aipPromedio": 25.985
 },
 {
  "id_dep": 2,
  "departamento": "El Progreso",
  "id_municipal": 201,
  "municipio": "Guastatoya",
  "aip2019": 88.57000000000001,
  "aip2017": 44.44,
  "aipPromedio": 66.505
 },
 {
  "id_dep": 2,
  "departamento": "El Progreso",
  "id_municipal": 202,
  "municipio": "Morazán",
  "aip2019": 78.57,
  "aip2017": 0,
  "aipPromedio": 39.285
 },
 {
  "id_dep": 2,
  "departamento": "El Progreso",
  "id_municipal": 203,
  "municipio": "San Agustín Acasaguastlán",
  "aip2019": 8.110000000000001,
  "aip2017": 0,
  "aipPromedio": 4.055
 },
 {
  "id_dep": 2,
  "departamento": "El Progreso",
  "id_municipal": 208,
  "municipio": "San Antonio La Paz",
  "aip2019": 15.79,
  "aip2017": 0,
  "aipPromedio": 7.895
 },
 {
  "id_dep": 2,
  "departamento": "El Progreso",
  "id_municipal": 204,
  "municipio": "San Cristóbal Acasaguastlán",
  "aip2019": 38.57,
  "aip2017": 0,
  "aipPromedio": 19.285
 },
 {
  "id_dep": 2,
  "departamento": "El Progreso",
  "id_municipal": 207,
  "municipio": "Sanarate",
  "aip2019": 10.53,
  "aip2017": 0,
  "aipPromedio": 5.265
 },
 {
  "id_dep": 2,
  "departamento": "El Progreso",
  "id_municipal": 206,
  "municipio": "Sansare",
  "aip2019": 44.59,
  "aip2017": 0,
  "aipPromedio": 22.295
 },
 {
  "id_dep": 5,
  "departamento": "Escuintla",
  "id_municipal": 501,
  "municipio": "Escuintla",
  "aip2019": 47.370000000000005,
  "aip2017": 45,
  "aip2015": 11.25,
  "aip2015insitu": 57.24,
  "aipPromedio": 34.54
 },
 {
  "id_dep": 5,
  "departamento": "Escuintla",
  "id_municipal": 508,
  "municipio": "Guanagazapa",
  "aip2019": 0,
  "aip2017": 0,
  "aipPromedio": 0
 },
 {
  "id_dep": 5,
  "departamento": "Escuintla",
  "id_municipal": 510,
  "municipio": "Iztapa",
  "aip2019": 26.32,
  "aip2017": 0,
  "aipPromedio": 13.16
 },
 {
  "id_dep": 5,
  "departamento": "Escuintla",
  "id_municipal": 503,
  "municipio": "La Democracia",
  "aip2019": 2.63,
  "aip2017": 0,
  "aipPromedio": 1.315
 },
 {
  "id_dep": 5,
  "departamento": "Escuintla",
  "id_municipal": 507,
  "municipio": "La Gomera",
  "aip2019": 75,
  "aip2017": 0,
  "aipPromedio": 37.5
 },
 {
  "id_dep": 5,
  "departamento": "Escuintla",
  "id_municipal": 505,
  "municipio": "Masagua",
  "aip2019": 35,
  "aip2017": 85.71,
  "aipPromedio": 60.355
 },
 {
  "id_dep": 5,
  "departamento": "Escuintla",
  "id_municipal": 513,
  "municipio": "Nueva Concepción",
  "aip2019": 22.37,
  "aip2017": 50,
  "aipPromedio": 36.185
 },
 {
  "id_dep": 5,
  "departamento": "Escuintla",
  "id_municipal": 511,
  "municipio": "Palín",
  "aip2019": 0,
  "aip2017": 0,
  "aipPromedio": 0
 },
 {
  "id_dep": 5,
  "departamento": "Escuintla",
  "id_municipal": 509,
  "municipio": "San José",
  "aip2019": 17.11,
  "aip2017": 0,
  "aipPromedio": 8.555
 },
 {
  "id_dep": 5,
  "departamento": "Escuintla",
  "id_municipal": 512,
  "municipio": "San Vicente Pacaya",
  "aip2019": 0,
  "aip2017": 0,
  "aipPromedio": 0
 },
 {
  "id_dep": 5,
  "departamento": "Escuintla",
  "id_municipal": 502,
  "municipio": "Santa Lucía Cotzulmalguapa",
  "aip2019": 26.32,
  "aip2017": 9.09,
  "aipPromedio": 17.705
 },
 {
  "id_dep": 5,
  "departamento": "Escuintla",
  "id_municipal": 514,
  "municipio": "Sipacate",
  "aip2019": 65.38000000000001,
  "aip2017": 64.29,
  "aipPromedio": 64.835
 },
 {
  "id_dep": 5,
  "departamento": "Escuintla",
  "id_municipal": 504,
  "municipio": "Siquinalá",
  "aip2019": 0,
  "aip2017": 10,
  "aip2015": 6.25,
  "aip2015insitu": 84.21,
  "aipPromedio": 5.416666667
 },
 {
  "id_dep": 5,
  "departamento": "Escuintla",
  "id_municipal": 506,
  "municipio": "Tiquisate",
  "aip2019": 21.21,
  "aip2017": 44.44,
  "aip2015": 0,
  "aip2015insitu": 11.11,
  "aipPromedio": 21.88333333
 },
 {
  "id_dep": 1,
  "departamento": "Guatemala",
  "id_municipal": 114,
  "municipio": "Amatitlán",
  "aip2019": 33.33,
  "aip2017": 61.11,
  "aip2015": 10,
  "aip2015insitu": 11.11,
  "aipPromedio": 34.81333333
 },
 {
  "id_dep": 1,
  "departamento": "Guatemala",
  "id_municipal": 106,
  "municipio": "Chinautla",
  "aip2019": 33.33,
  "aip2017": 44.44,
  "aip2015": 10,
  "aip2015insitu": 6.7,
  "aipPromedio": 29.25666667
 },
 {
  "id_dep": 1,
  "departamento": "Guatemala",
  "id_municipal": 112,
  "municipio": "Chuarrancho",
  "aip2019": 31.25,
  "aip2017": 35,
  "aip2015": 0,
  "aip2015insitu": 71.31,
  "aipPromedio": 22.08333333
 },
 {
  "id_dep": 1,
  "departamento": "Guatemala",
  "id_municipal": 113,
  "municipio": "Fraijanes",
  "aip2019": 44.74,
  "aip2017": 83.33,
  "aip2015": 29.42,
  "aip2015insitu": 73.08,
  "aipPromedio": 52.49666667
 },
 {
  "id_dep": 1,
  "departamento": "Guatemala",
  "id_municipal": 101,
  "municipio": "Guatemala",
  "aip2019": 67.94,
  "aip2017": 83.33,
  "aip2015": 95.72,
  "aip2015insitu": 90.4,
  "aipPromedio": 82.33
 },
 {
  "id_dep": 1,
  "departamento": "Guatemala",
  "id_municipal": 108,
  "municipio": "Mixco",
  "aip2019": 58.330000000000005,
  "aip2017": 35.71,
  "aip2015": 8.13,
  "aip2015insitu": 25.61,
  "aipPromedio": 34.05666667
 },
 {
  "id_dep": 1,
  "departamento": "Guatemala",
  "id_municipal": 105,
  "municipio": "Palencia",
  "aip2019": 55.00000000000001,
  "aip2017": 64.29,
  "aip2015": 26.56,
  "aip2015insitu": 55.75,
  "aipPromedio": 48.61666667
 },
 {
  "id_dep": 1,
  "departamento": "Guatemala",
  "id_municipal": 104,
  "municipio": "San José del Golfo",
  "aip2019": 79.73,
  "aip2017": 100,
  "aip2015": 0,
  "aip2015insitu": 27.78,
  "aipPromedio": 59.91
 },
 {
  "id_dep": 1,
  "departamento": "Guatemala",
  "id_municipal": 103,
  "municipio": "San José Pinula",
  "aip2019": 63.239999999999995,
  "aip2017": 85.71,
  "aip2015": 7.5,
  "aip2015insitu": 79.7,
  "aipPromedio": 52.15
 },
 {
  "id_dep": 1,
  "departamento": "Guatemala",
  "id_municipal": 110,
  "municipio": "San Juan Sacatepéquez",
  "aip2019": 10.53,
  "aip2017": 56.25,
  "aip2015": 77.19,
  "aip2015insitu": 58.96,
  "aipPromedio": 47.99
 },
 {
  "id_dep": 1,
  "departamento": "Guatemala",
  "id_municipal": 117,
  "municipio": "San Miguel Petapa",
  "aip2019": 26.92,
  "aip2017": 35,
  "aip2015": 7.5,
  "aip2015insitu": 0,
  "aipPromedio": 23.14
 },
 {
  "id_dep": 1,
  "departamento": "Guatemala",
  "id_municipal": 107,
  "municipio": "San Pedro Ayampuc",
  "aip2019": 61.42999999999999,
  "aip2017": 71.43,
  "aip2015": 0,
  "aip2015insitu": 22.22,
  "aipPromedio": 44.28666667
 },
 {
  "id_dep": 1,
  "departamento": "Guatemala",
  "id_municipal": 109,
  "municipio": "San Pedro Sacatepéquez",
  "aip2019": 47.3,
  "aip2017": 81.25,
  "aip2015": 12.97,
  "aip2015insitu": 48.42,
  "aipPromedio": 47.17333333
 },
 {
  "id_dep": 1,
  "departamento": "Guatemala",
  "id_municipal": 111,
  "municipio": "San Raymundo",
  "aip2019": 89.39,
  "aip2017": 35.71,
  "aip2015": 0,
  "aip2015insitu": 53.26,
  "aipPromedio": 41.7
 },
 {
  "id_dep": 1,
  "departamento": "Guatemala",
  "id_municipal": 102,
  "municipio": "Santa Catarina Pinula",
  "aip2019": 63.89,
  "aip2017": 75,
  "aip2015": 87.34,
  "aip2015insitu": 86.11,
  "aipPromedio": 75.41
 },
 {
  "id_dep": 1,
  "departamento": "Guatemala",
  "id_municipal": 116,
  "municipio": "Villa Canales",
  "aip2019": 54.55,
  "aip2017": 68.75,
  "aip2015": 44.75,
  "aip2015insitu": 49,
  "aipPromedio": 56.01666667
 },
 {
  "id_dep": 1,
  "departamento": "Guatemala",
  "id_municipal": 115,
  "municipio": "Villa Nueva",
  "aip2019": 72.06,
  "aip2017": 61.11,
  "aip2015": 55.12,
  "aip2015insitu": 77.7,
  "aipPromedio": 62.76333333
 },
 {
  "id_dep": 13,
  "departamento": "Huehuetenango",
  "id_municipal": 1327,
  "municipio": "Aguacatán",
  "aip2019": 61.25000000000001,
  "aip2017": 45,
  "aip2015": 0,
  "aip2015insitu": 47.26,
  "aipPromedio": 35.41666667
 },
 {
  "id_dep": 13,
  "departamento": "Huehuetenango",
  "id_municipal": 1302,
  "municipio": "Chiantla",
  "aip2019": 17.5,
  "aip2017": 0,
  "aipPromedio": 8.75
 },
 {
  "id_dep": 13,
  "departamento": "Huehuetenango",
  "id_municipal": 1319,
  "municipio": "Colotenango",
  "aip2019": 0,
  "aip2017": 0,
  "aip2015": 0,
  "aip2015insitu": 84.74,
  "aipPromedio": 0
 },
 {
  "id_dep": 13,
  "departamento": "Huehuetenango",
  "id_municipal": 1322,
  "municipio": "Concepción Huista",
  "aip2019": 20.59,
  "aip2017": 38.89,
  "aip2015": 0,
  "aip2015insitu": 66.81,
  "aipPromedio": 19.82666667
 },
 {
  "id_dep": 13,
  "departamento": "Huehuetenango",
  "id_municipal": 1304,
  "municipio": "Cuilco",
  "aip2019": 87.88,
  "aip2017": 0,
  "aipPromedio": 43.94
 },
 {
  "id_dep": 13,
  "departamento": "Huehuetenango",
  "id_municipal": 1301,
  "municipio": "Huehuetenango",
  "aip2019": 52.559999999999995,
  "aip2017": 30,
  "aipPromedio": 41.28
 },
 {
  "id_dep": 13,
  "departamento": "Huehuetenango",
  "id_municipal": 1307,
  "municipio": "Jacaltenango",
  "aip2019": 47.06,
  "aip2017": 38.89,
  "aipPromedio": 42.975
 },
 {
  "id_dep": 13,
  "departamento": "Huehuetenango",
  "id_municipal": 1312,
  "municipio": "La Democracia",
  "aip2019": 63.79,
  "aip2017": 44.44,
  "aip2015": 2.5,
  "aip2015insitu": 68.63,
  "aipPromedio": 36.91
 },
 {
  "id_dep": 13,
  "departamento": "Huehuetenango",
  "id_municipal": 1311,
  "municipio": "La Libertad",
  "aip2019": 31.819999999999997,
  "aip2017": 0,
  "aip2015": 0,
  "aip2015insitu": 72.32,
  "aipPromedio": 10.60666667
 },
 {
  "id_dep": 13,
  "departamento": "Huehuetenango",
  "id_municipal": 1303,
  "municipio": "Malacatancito",
  "aip2019": 61.53999999999999,
  "aip2017": 0,
  "aipPromedio": 30.77
 },
 {
  "id_dep": 13,
  "departamento": "Huehuetenango",
  "id_municipal": 1305,
  "municipio": "Nentón",
  "aip2019": 23.53,
  "aip2017": 15,
  "aip2015": 0,
  "aip2015insitu": 60.83,
  "aipPromedio": 12.84333333
 },
 {
  "id_dep": 13,
  "departamento": "Huehuetenango",
  "id_municipal": 1333,
  "municipio": "Petatán",
  "aip2019": 43.55,
  "aip2017": 15,
  "aipPromedio": 29.275
 },
 {
  "id_dep": 13,
  "departamento": "Huehuetenango",
  "id_municipal": 1324,
  "municipio": "San Antonio Huista",
  "aip2019": 48.48,
  "aip2017": 0,
  "aip2015": 0,
  "aip2015insitu": 29.25,
  "aipPromedio": 16.16
 },
 {
  "id_dep": 13,
  "departamento": "Huehuetenango",
  "id_municipal": 1329,
  "municipio": "San Gaspar Ixchil",
  "aip2019": 67.19000000000001,
  "aip2017": 0,
  "aipPromedio": 33.595
 },
 {
  "id_dep": 13,
  "departamento": "Huehuetenango",
  "id_municipal": 1309,
  "municipio": "San Idelfonso Ixtahuacán",
  "aip2019": 53.13,
  "aip2017": 45,
  "aipPromedio": 49.065
 },
 {
  "id_dep": 13,
  "departamento": "Huehuetenango",
  "id_municipal": 1316,
  "municipio": "San Juan Atitán",
  "aip2019": 21.790000000000003,
  "aip2017": 38.89,
  "aip2015": 0,
  "aip2015insitu": 78.48,
  "aipPromedio": 20.22666667
 },
 {
  "id_dep": 13,
  "departamento": "Huehuetenango",
  "id_municipal": 1323,
  "municipio": "San Juan Ixcoy",
  "aip2019": 0,
  "aip2017": 0,
  "aipPromedio": 0
 },
 {
  "id_dep": 13,
  "departamento": "Huehuetenango",
  "id_municipal": 1318,
  "municipio": "San Mateo Ixtatán",
  "aip2019": 0,
  "aip2017": 0,
  "aipPromedio": 0
 },
 {
  "id_dep": 13,
  "departamento": "Huehuetenango",
  "id_municipal": 1313,
  "municipio": "San Miguel Acatán",
  "aip2019": 48.48,
  "aip2017": 20,
  "aip2015": 0,
  "aip2015insitu": 30.31,
  "aipPromedio": 22.82666667
 },
 {
  "id_dep": 13,
  "departamento": "Huehuetenango",
  "id_municipal": 1306,
  "municipio": "San Pedro Necta",
  "aip2019": 19.23,
  "aip2017": 0,
  "aipPromedio": 9.615
 },
 {
  "id_dep": 13,
  "departamento": "Huehuetenango",
  "id_municipal": 1308,
  "municipio": "San Pedro Soloma",
  "aip2019": 11.11,
  "aip2017": 0,
  "aipPromedio": 5.555
 },
 {
  "id_dep": 13,
  "departamento": "Huehuetenango",
  "id_municipal": 1314,
  "municipio": "San Rafael La Independencia",
  "aip2019": 20.97,
  "aip2017": 10,
  "aip2015": 0,
  "aip2015insitu": 30.68,
  "aipPromedio": 10.32333333
 },
 {
  "id_dep": 13,
  "departamento": "Huehuetenango",
  "id_municipal": 1328,
  "municipio": "San Rafael Pétzal",
  "aip2019": 22.22,
  "aip2017": 20,
  "aip2015": 0,
  "aip2015insitu": 11.31,
  "aipPromedio": 14.07333333
 },
 {
  "id_dep": 13,
  "departamento": "Huehuetenango",
  "id_municipal": 1325,
  "municipio": "San Sebastián Coatán",
  "aip2019": 12.12,
  "aip2017": 45,
  "aip2015": 0,
  "aip2015insitu": 24.54,
  "aipPromedio": 19.04
 },
 {
  "id_dep": 13,
  "departamento": "Huehuetenango",
  "id_municipal": 1320,
  "municipio": "San Sebastián Huehuetenango",
  "aip2019": 14.29,
  "aip2017": 25,
  "aip2015": 0,
  "aip2015insitu": 52.03,
  "aipPromedio": 13.09666667
 },
 {
  "id_dep": 13,
  "departamento": "Huehuetenango",
  "id_municipal": 1331,
  "municipio": "Santa Ana Huista",
  "aip2019": 17.11,
  "aip2017": 0,
  "aip2015": 0,
  "aip2015insitu": 84.09,
  "aipPromedio": 5.703333333
 },
 {
  "id_dep": 13,
  "departamento": "Huehuetenango",
  "id_municipal": 1310,
  "municipio": "Santa Bárbara",
  "aip2019": 68.17999999999999,
  "aip2017": 10,
  "aipPromedio": 39.09
 },
 {
  "id_dep": 13,
  "departamento": "Huehuetenango",
  "id_municipal": 1326,
  "municipio": "Barillas",
  "aip2019": 0,
  "aip2017": 0,
  "aip2015": 0,
  "aip2015insitu": 55.37,
  "aipPromedio": 0
 },
 {
  "id_dep": 13,
  "departamento": "Huehuetenango",
  "id_municipal": 1317,
  "municipio": "Santa Eulalia",
  "aip2019": 5.26,
  "aip2017": 0,
  "aipPromedio": 2.63
 },
 {
  "id_dep": 13,
  "departamento": "Huehuetenango",
  "id_municipal": 1330,
  "municipio": "Santiago Chimaltenango",
  "aip2019": 40.910000000000004,
  "aip2017": 0,
  "aip2015": 0,
  "aip2015insitu": 68.47,
  "aipPromedio": 13.63666667
 },
 {
  "id_dep": 13,
  "departamento": "Huehuetenango",
  "id_municipal": 1321,
  "municipio": "Tectitán",
  "aip2019": 16.25,
  "aip2017": 10,
  "aip2015": 0,
  "aip2015insitu": 65.18,
  "aipPromedio": 8.75
 },
 {
  "id_dep": 13,
  "departamento": "Huehuetenango",
  "id_municipal": 1315,
  "municipio": "Todos Santos Cuchumatán",
  "aip2019": 39.660000000000004,
  "aip2017": 0,
  "aipPromedio": 19.83
 },
 {
  "id_dep": 13,
  "departamento": "Huehuetenango",
  "id_municipal": 1332,
  "municipio": "Unión Cantinil",
  "aip2019": 27.589999999999996,
  "aip2017": 27.78,
  "aip2015": 0,
  "aip2015insitu": 60.28,
  "aipPromedio": 18.45666667
 },
 {
  "id_dep": 18,
  "departamento": "Izabal",
  "id_municipal": 1803,
  "municipio": "El Estor",
  "aip2019": 62.16,
  "aip2017": 51.85,
  "aipPromedio": 57.005
 },
 {
  "id_dep": 18,
  "departamento": "Izabal",
  "id_municipal": 1802,
  "municipio": "Livingston",
  "aip2019": 62.5,
  "aip2017": 0,
  "aipPromedio": 31.25
 },
 {
  "id_dep": 18,
  "departamento": "Izabal",
  "id_municipal": 1805,
  "municipio": "Los Amates",
  "aip2019": 86.76,
  "aip2017": 40,
  "aip2015": 0,
  "aip2015insitu": 76.11,
  "aipPromedio": 42.25333333
 },
 {
  "id_dep": 18,
  "departamento": "Izabal",
  "id_municipal": 1804,
  "municipio": "Morales",
  "aip2019": 13.750000000000002,
  "aip2017": 0,
  "aipPromedio": 6.875
 },
 {
  "id_dep": 18,
  "departamento": "Izabal",
  "id_municipal": 1801,
  "municipio": "Puerto Barrios",
  "aip2019": 65.63,
  "aip2017": 0,
  "aip2015": 27.85,
  "aip2015insitu": 11.11,
  "aipPromedio": 31.16
 },
 {
  "id_dep": 21,
  "departamento": "Jalapa",
  "id_municipal": 2101,
  "municipio": "Jalapa",
  "aip2019": 23.68,
  "aip2017": 0,
  "aipPromedio": 11.84
 },
 {
  "id_dep": 21,
  "departamento": "Jalapa",
  "id_municipal": 2107,
  "municipio": "Mataquescuintla",
  "aip2019": 89.47,
  "aip2017": 0,
  "aip2015": 0,
  "aip2015insitu": 41.6,
  "aipPromedio": 29.82333333
 },
 {
  "id_dep": 21,
  "departamento": "Jalapa",
  "id_municipal": 2106,
  "municipio": "Monjas",
  "aip2019": 68.75,
  "aip2017": 40,
  "aip2015": 0,
  "aip2015insitu": 20.45,
  "aipPromedio": 36.25
 },
 {
  "id_dep": 21,
  "departamento": "Jalapa",
  "id_municipal": 2105,
  "municipio": "San Carlos Alzatate",
  "aip2019": 40.54,
  "aip2017": 0,
  "aipPromedio": 20.27
 },
 {
  "id_dep": 21,
  "departamento": "Jalapa",
  "id_municipal": 2103,
  "municipio": "San Luis Jilotepeque",
  "aip2019": 18.42,
  "aip2017": 35,
  "aip2015": 0,
  "aip2015insitu": 73.26,
  "aipPromedio": 17.80666667
 },
 {
  "id_dep": 21,
  "departamento": "Jalapa",
  "id_municipal": 2104,
  "municipio": "San Manuel Chaparrón",
  "aip2019": 71.05,
  "aip2017": 0,
  "aip2015": 0,
  "aip2015insitu": 20.83,
  "aipPromedio": 23.68333333
 },
 {
  "id_dep": 21,
  "departamento": "Jalapa",
  "id_municipal": 2102,
  "municipio": "San Pedro Pinula",
  "aip2019": 12.16,
  "aip2017": 0,
  "aip2015": 0,
  "aip2015insitu": 0,
  "aipPromedio": 4.053333333
 },
 {
  "id_dep": 22,
  "departamento": "Jutiapa",
  "id_municipal": 2204,
  "municipio": "Agua Blanca",
  "aip2019": 90.53999999999999,
  "aip2017": 75,
  "aip2015": 13.75,
  "aip2015insitu": 83.33,
  "aipPromedio": 59.76333333
 },
 {
  "id_dep": 22,
  "departamento": "Jutiapa",
  "id_municipal": 2205,
  "municipio": "Asunción Mita",
  "aip2019": 76.25,
  "aip2017": 18.75,
  "aip2015": 8.75,
  "aip2015insitu": 88.08,
  "aipPromedio": 34.58333333
 },
 {
  "id_dep": 22,
  "departamento": "Jutiapa",
  "id_municipal": 2207,
  "municipio": "Atescatempa",
  "aip2019": 67.57,
  "aip2017": 57.14,
  "aip2015": 9.11,
  "aip2015insitu": 76.19,
  "aipPromedio": 44.60666667
 },
 {
  "id_dep": 22,
  "departamento": "Jutiapa",
  "id_municipal": 2211,
  "municipio": "Comapa",
  "aip2019": 11.25,
  "aip2017": 25,
  "aip2015": 0,
  "aip2015insitu": 81.08,
  "aipPromedio": 12.08333333
 },
 {
  "id_dep": 22,
  "departamento": "Jutiapa",
  "id_municipal": 2213,
  "municipio": "Conguaco",
  "aip2019": 86.83999999999999,
  "aip2017": 6.06,
  "aipPromedio": 46.45
 },
 {
  "id_dep": 22,
  "departamento": "Jutiapa",
  "id_municipal": 2209,
  "municipio": "El Adelanto",
  "aip2019": 71.25,
  "aip2017": 14.29,
  "aip2015": 0,
  "aip2015insitu": 90.23,
  "aipPromedio": 28.51333333
 },
 {
  "id_dep": 22,
  "departamento": "Jutiapa",
  "id_municipal": 2202,
  "municipio": "El Progreso",
  "aip2019": 92.31,
  "aip2017": 0,
  "aipPromedio": 46.155
 },
 {
  "id_dep": 22,
  "departamento": "Jutiapa",
  "id_municipal": 2212,
  "municipio": "Jalpatagua",
  "aip2019": 75,
  "aip2017": 6.06,
  "aipPromedio": 40.53
 },
 {
  "id_dep": 22,
  "departamento": "Jutiapa",
  "id_municipal": 2208,
  "municipio": "Jerez",
  "aip2019": 81.58,
  "aip2017": 64.29,
  "aip2015": 47.99,
  "aip2015insitu": 87.32,
  "aipPromedio": 64.62
 },
 {
  "id_dep": 22,
  "departamento": "Jutiapa",
  "id_municipal": 2201,
  "municipio": "Jutiapa",
  "aip2019": 55.00000000000001,
  "aip2017": 24.31,
  "aipPromedio": 39.655
 },
 {
  "id_dep": 22,
  "departamento": "Jutiapa",
  "id_municipal": 2214,
  "municipio": "Moyuta",
  "aip2019": 78.75,
  "aip2017": 0,
  "aipPromedio": 39.375
 },
 {
  "id_dep": 22,
  "departamento": "Jutiapa",
  "id_municipal": 2215,
  "municipio": "Pasaco",
  "aip2019": 25,
  "aip2017": 0,
  "aip2015": 0,
  "aip2015insitu": 84.62,
  "aipPromedio": 8.333333333
 },
 {
  "id_dep": 22,
  "departamento": "Jutiapa",
  "id_municipal": 2217,
  "municipio": "Quesada",
  "aip2019": 62.5,
  "aip2017": 50,
  "aip2015": 0,
  "aip2015insitu": 85,
  "aipPromedio": 37.5
 },
 {
  "id_dep": 22,
  "departamento": "Jutiapa",
  "id_municipal": 2216,
  "municipio": "San José Acatempa",
  "aip2019": 42.5,
  "aip2017": 42.86,
  "aip2015": 0,
  "aip2015insitu": 79.49,
  "aipPromedio": 28.45333333
 },
 {
  "id_dep": 22,
  "departamento": "Jutiapa",
  "id_municipal": 2203,
  "municipio": "Santa Catarina Mita",
  "aip2019": 50,
  "aip2017": 42.86,
  "aip2015": 2.5,
  "aip2015insitu": 94.5,
  "aipPromedio": 31.78666667
 },
 {
  "id_dep": 22,
  "departamento": "Jutiapa",
  "id_municipal": 2206,
  "municipio": "Yupiltepeque",
  "aip2019": 79.49000000000001,
  "aip2017": 35.71,
  "aip2015": 60.2,
  "aip2015insitu": 83.98,
  "aipPromedio": 58.46666667
 },
 {
  "id_dep": 22,
  "departamento": "Jutiapa",
  "id_municipal": 2210,
  "municipio": "Zapotitlán",
  "aip2019": 83.75,
  "aip2017": 35.71,
  "aip2015": 0,
  "aip2015insitu": 95.24,
  "aipPromedio": 39.82
 },
 {
  "id_dep": 17,
  "departamento": "Petén",
  "id_municipal": 1708,
  "municipio": "Dolores",
  "aip2019": 36.84,
  "aip2017": 0,
  "aipPromedio": 18.42
 },
 {
  "id_dep": 17,
  "departamento": "Petén",
  "id_municipal": 1714,
  "municipio": "El Chal",
  "aip2019": 71.25,
  "aip2017": 20,
  "aip2015": 0,
  "aip2015insitu": 8.89,
  "aipPromedio": 30.41666667
 },
 {
  "id_dep": 17,
  "departamento": "Petén",
  "id_municipal": 1701,
  "municipio": "Flores",
  "aip2019": 27.42,
  "aip2017": 50,
  "aipPromedio": 38.71
 },
 {
  "id_dep": 17,
  "departamento": "Petén",
  "id_municipal": 1705,
  "municipio": "La Libertad",
  "aip2019": 7.89,
  "aip2017": 0,
  "aip2015": 0,
  "aip2015insitu": 80.8,
  "aipPromedio": 2.63
 },
 {
  "id_dep": 17,
  "departamento": "Petén",
  "id_municipal": 1713,
  "municipio": "Las Cruces",
  "aip2019": 7.5,
  "aip2017": 0,
  "aip2015": 0,
  "aip2015insitu": 67.44,
  "aipPromedio": 2.5
 },
 {
  "id_dep": 17,
  "departamento": "Petén",
  "id_municipal": 1711,
  "municipio": "Melchor de Mencos",
  "aip2019": 24.36,
  "aip2017": 0,
  "aipPromedio": 12.18
 },
 {
  "id_dep": 17,
  "departamento": "Petén",
  "id_municipal": 1712,
  "municipio": "Poptún",
  "aip2019": 44.74,
  "aip2017": 0,
  "aipPromedio": 22.37
 },
 {
  "id_dep": 17,
  "departamento": "Petén",
  "id_municipal": 1704,
  "municipio": "San Andrés",
  "aip2019": 76.47,
  "aip2017": 56.25,
  "aip2015": 0,
  "aip2015insitu": 80,
  "aipPromedio": 44.24
 },
 {
  "id_dep": 17,
  "departamento": "Petén",
  "id_municipal": 1703,
  "municipio": "San Benito",
  "aip2019": 42.309999999999995,
  "aip2017": 20,
  "aipPromedio": 31.155
 },
 {
  "id_dep": 17,
  "departamento": "Petén",
  "id_municipal": 1706,
  "municipio": "San Francisco",
  "aip2019": 23.75,
  "aip2017": 0,
  "aipPromedio": 11.875
 },
 {
  "id_dep": 17,
  "departamento": "Petén",
  "id_municipal": 1702,
  "municipio": "San José",
  "aip2019": 0,
  "aip2017": 0,
  "aip2015": 0,
  "aip2015insitu": 70.28,
  "aipPromedio": 0
 },
 {
  "id_dep": 17,
  "departamento": "Petén",
  "id_municipal": 1709,
  "municipio": "San Luis",
  "aip2019": 12.5,
  "aip2017": 0,
  "aipPromedio": 6.25
 },
 {
  "id_dep": 17,
  "departamento": "Petén",
  "id_municipal": 1707,
  "municipio": "Santa Ana",
  "aip2019": 0,
  "aip2017": 15,
  "aip2015": 0,
  "aip2015insitu": 50,
  "aipPromedio": 5
 },
 {
  "id_dep": 17,
  "departamento": "Petén",
  "id_municipal": 1710,
  "municipio": "Sayaxché",
  "aip2019": 7.5,
  "aip2017": 0,
  "aip2015": 0,
  "aip2015insitu": 61.11,
  "aipPromedio": 2.5
 },
 {
  "id_dep": 9,
  "departamento": "Quetzaltenango",
  "id_municipal": 913,
  "municipio": "Almolonga",
  "aip2019": 22.5,
  "aip2017": 25,
  "aip2015": 44.38,
  "aip2015insitu": 74.02,
  "aipPromedio": 30.62666667
 },
 {
  "id_dep": 9,
  "departamento": "Quetzaltenango",
  "id_municipal": 906,
  "municipio": "Cabricán",
  "aip2019": 58.330000000000005,
  "aip2017": 0,
  "aip2015": 0,
  "aip2015insitu": 75,
  "aipPromedio": 19.44333333
 },
 {
  "id_dep": 9,
  "departamento": "Quetzaltenango",
  "id_municipal": 907,
  "municipio": "Cajolá",
  "aip2019": 0,
  "aip2017": 0,
  "aipPromedio": 0
 },
 {
  "id_dep": 9,
  "departamento": "Quetzaltenango",
  "id_municipal": 914,
  "municipio": "Cantel",
  "aip2019": 78.95,
  "aip2017": 0,
  "aipPromedio": 39.475
 },
 {
  "id_dep": 9,
  "departamento": "Quetzaltenango",
  "id_municipal": 920,
  "municipio": "Coatepeque",
  "aip2019": 21.25,
  "aip2017": 30,
  "aip2015": 0,
  "aip2015insitu": 32.35,
  "aipPromedio": 17.08333333
 },
 {
  "id_dep": 9,
  "departamento": "Quetzaltenango",
  "id_municipal": 917,
  "municipio": "Colomba",
  "aip2019": 13.239999999999998,
  "aip2017": 0,
  "aip2015": 0,
  "aip2015insitu": 38.91,
  "aipPromedio": 4.413333333
 },
 {
  "id_dep": 9,
  "departamento": "Quetzaltenango",
  "id_municipal": 911,
  "municipio": "Concepción Chiquirichapa",
  "aip2019": 82.5,
  "aip2017": 60,
  "aip2015": 34.69,
  "aip2015insitu": 75.76,
  "aipPromedio": 59.06333333
 },
 {
  "id_dep": 9,
  "departamento": "Quetzaltenango",
  "id_municipal": 919,
  "municipio": "El Palmar",
  "aip2019": 80,
  "aip2017": 80,
  "aip2015": 0,
  "aip2015insitu": 73.17,
  "aipPromedio": 53.33333333
 },
 {
  "id_dep": 9,
  "departamento": "Quetzaltenango",
  "id_municipal": 922,
  "municipio": "Flores Costa Cuca",
  "aip2019": 2.7,
  "aip2017": 0,
  "aip2015": 0,
  "aip2015insitu": 56.42,
  "aipPromedio": 0.9
 },
 {
  "id_dep": 9,
  "departamento": "Quetzaltenango",
  "id_municipal": 921,
  "municipio": "Génova",
  "aip2019": 0,
  "aip2017": 56.25,
  "aip2015": 0,
  "aip2015insitu": 45.25,
  "aipPromedio": 18.75
 },
 {
  "id_dep": 9,
  "departamento": "Quetzaltenango",
  "id_municipal": 915,
  "municipio": "Huitán",
  "aip2019": 72.5,
  "aip2017": 50,
  "aip2015": 0,
  "aip2015insitu": 0,
  "aipPromedio": 40.83333333
 },
 {
  "id_dep": 9,
  "departamento": "Quetzaltenango",
  "id_municipal": 923,
  "municipio": "La Esperanza",
  "aip2019": 47.5,
  "aip2017": 30,
  "aip2015": 0,
  "aip2015insitu": 62.22,
  "aipPromedio": 25.83333333
 },
 {
  "id_dep": 9,
  "departamento": "Quetzaltenango",
  "id_municipal": 903,
  "municipio": "Olintepeque",
  "aip2019": 88.75,
  "aip2017": 0,
  "aip2015": 10,
  "aip2015insitu": 86.17,
  "aipPromedio": 32.91666667
 },
 {
  "id_dep": 9,
  "departamento": "Quetzaltenango",
  "id_municipal": 924,
  "municipio": "Palestina de los Altos",
  "aip2019": 76.32,
  "aip2017": 0,
  "aipPromedio": 38.16
 },
 {
  "id_dep": 9,
  "departamento": "Quetzaltenango",
  "id_municipal": 901,
  "municipio": "Quetzaltenango",
  "aip2019": 43.75,
  "aip2017": 40,
  "aipPromedio": 41.875
 },
 {
  "id_dep": 9,
  "departamento": "Quetzaltenango",
  "id_municipal": 902,
  "municipio": "Salcajá",
  "aip2019": 71.05,
  "aip2017": 56.25,
  "aip2015": 0,
  "aip2015insitu": 86.33,
  "aipPromedio": 42.43333333
 },
 {
  "id_dep": 9,
  "departamento": "Quetzaltenango",
  "id_municipal": 904,
  "municipio": "San Carlos Sija",
  "aip2019": 35,
  "aip2017": 15,
  "aip2015": 0,
  "aip2015insitu": 78.47,
  "aipPromedio": 16.66666667
 },
 {
  "id_dep": 9,
  "departamento": "Quetzaltenango",
  "id_municipal": 918,
  "municipio": "San Francisco La Unión",
  "aip2019": 22.5,
  "aip2017": 0,
  "aipPromedio": 11.25
 },
 {
  "id_dep": 9,
  "departamento": "Quetzaltenango",
  "id_municipal": 909,
  "municipio": "San Juan Ostuncalco",
  "aip2019": 84.21,
  "aip2017": 0,
  "aipPromedio": 42.105
 },
 {
  "id_dep": 9,
  "departamento": "Quetzaltenango",
  "id_municipal": 912,
  "municipio": "San Martín Sacatepéquez",
  "aip2019": 0,
  "aip2017": 55.56,
  "aipPromedio": 27.78
 },
 {
  "id_dep": 9,
  "departamento": "Quetzaltenango",
  "id_municipal": 910,
  "municipio": "San Mateo",
  "aip2019": 30,
  "aip2017": 0,
  "aipPromedio": 15
 },
 {
  "id_dep": 9,
  "departamento": "Quetzaltenango",
  "id_municipal": 908,
  "municipio": "San Miguel Sigüila",
  "aip2019": 0,
  "aip2017": 0,
  "aipPromedio": 0
 },
 {
  "id_dep": 9,
  "departamento": "Quetzaltenango",
  "id_municipal": 905,
  "municipio": "Sibilia",
  "aip2019": 88.75,
  "aip2017": 75,
  "aip2015": 27.78,
  "aip2015insitu": 86.87,
  "aipPromedio": 63.84333333
 },
 {
  "id_dep": 9,
  "departamento": "Quetzaltenango",
  "id_municipal": 916,
  "municipio": "Zunil",
  "aip2019": 0,
  "aip2017": 10,
  "aipPromedio": 5
 },
 {
  "id_dep": 14,
  "departamento": "Quiché",
  "id_municipal": 1418,
  "municipio": "Canillá",
  "aip2019": 43.75,
  "aip2017": 0,
  "aip2015": 0,
  "aip2015insitu": 95.24,
  "aipPromedio": 14.58333333
 },
 {
  "id_dep": 14,
  "departamento": "Quiché",
  "id_municipal": 1405,
  "municipio": "Chajul",
  "aip2019": 10.53,
  "aip2017": 0,
  "aipPromedio": 5.265
 },
 {
  "id_dep": 14,
  "departamento": "Quiché",
  "id_municipal": 1419,
  "municipio": "Chicamán",
  "aip2019": 51.61,
  "aip2017": 64.29,
  "aip2015": 0,
  "aip2015insitu": 58.21,
  "aipPromedio": 38.63333333
 },
 {
  "id_dep": 14,
  "departamento": "Quiché",
  "id_municipal": 1402,
  "municipio": "Chiché",
  "aip2019": 62.12,
  "aip2017": 0,
  "aip2015": 0,
  "aip2015insitu": 47.54,
  "aipPromedio": 20.70666667
 },
 {
  "id_dep": 14,
  "departamento": "Quiché",
  "id_municipal": 1406,
  "municipio": "Chichicastenango",
  "aip2019": 71.88,
  "aip2017": 50,
  "aip2015": 0,
  "aip2015insitu": 45.51,
  "aipPromedio": 40.62666667
 },
 {
  "id_dep": 14,
  "departamento": "Quiché",
  "id_municipal": 1403,
  "municipio": "Chinique",
  "aip2019": 17.19,
  "aip2017": 10,
  "aipPromedio": 13.595
 },
 {
  "id_dep": 14,
  "departamento": "Quiché",
  "id_municipal": 1410,
  "municipio": "Cunén",
  "aip2019": 50,
  "aip2017": 0,
  "aip2015": 0,
  "aip2015insitu": 35.79,
  "aipPromedio": 16.66666667
 },
 {
  "id_dep": 14,
  "departamento": "Quiché",
  "id_municipal": 1412,
  "municipio": "Joyabaj",
  "aip2019": 21.25,
  "aip2017": 0,
  "aip2015": 0,
  "aip2015insitu": 94.99,
  "aipPromedio": 7.083333333
 },
 {
  "id_dep": 14,
  "departamento": "Quiché",
  "id_municipal": 1421,
  "municipio": "Pachalum",
  "aip2019": 81.03,
  "aip2017": 25,
  "aip2015": 3.13,
  "aip2015insitu": 88.34,
  "aipPromedio": 36.38666667
 },
 {
  "id_dep": 14,
  "departamento": "Quiché",
  "id_municipal": 1407,
  "municipio": "Patzité",
  "aip2019": 16.669999999999998,
  "aip2017": 30,
  "aipPromedio": 23.335
 },
 {
  "id_dep": 14,
  "departamento": "Quiché",
  "id_municipal": 1420,
  "municipio": "Ixcán",
  "aip2019": 21.62,
  "aip2017": 44.44,
  "aipPromedio": 33.03
 },
 {
  "id_dep": 14,
  "departamento": "Quiché",
  "id_municipal": 1416,
  "municipio": "Sacapulas",
  "aip2019": 46.05,
  "aip2017": 10,
  "aip2015": 0,
  "aip2015insitu": 78.05,
  "aipPromedio": 18.68333333
 },
 {
  "id_dep": 14,
  "departamento": "Quiché",
  "id_municipal": 1414,
  "municipio": "San Andrés Sajcabajá",
  "aip2019": 45.31,
  "aip2017": 10,
  "aip2015": 0,
  "aip2015insitu": 87.3,
  "aipPromedio": 18.43666667
 },
 {
  "id_dep": 14,
  "departamento": "Quiché",
  "id_municipal": 1408,
  "municipio": "San Antonio Ilotenango",
  "aip2019": 40,
  "aip2017": 58.33,
  "aipPromedio": 49.165
 },
 {
  "id_dep": 14,
  "departamento": "Quiché",
  "id_municipal": 1417,
  "municipio": "San Bartolomé Jocotenango",
  "aip2019": 27.78,
  "aip2017": 0,
  "aipPromedio": 13.89
 },
 {
  "id_dep": 14,
  "departamento": "Quiché",
  "id_municipal": 1411,
  "municipio": "San Juan Cotzal",
  "aip2019": 45.71,
  "aip2017": 20,
  "aipPromedio": 32.855
 },
 {
  "id_dep": 14,
  "departamento": "Quiché",
  "id_municipal": 1415,
  "municipio": "San Miguel Uspantán",
  "aip2019": 7.89,
  "aip2017": 25,
  "aip2015": 0,
  "aip2015insitu": 35.71,
  "aipPromedio": 10.96333333
 },
 {
  "id_dep": 14,
  "departamento": "Quiché",
  "id_municipal": 1409,
  "municipio": "San Pedro Jocopilas",
  "aip2019": 5.13,
  "aip2017": 10,
  "aipPromedio": 7.565
 },
 {
  "id_dep": 14,
  "departamento": "Quiché",
  "id_municipal": 1401,
  "municipio": "Santa Cruz del Quiché",
  "aip2019": 13.750000000000002,
  "aip2017": 25,
  "aipPromedio": 19.375
 },
 {
  "id_dep": 14,
  "departamento": "Quiché",
  "id_municipal": 1413,
  "municipio": "Nebaj",
  "aip2019": 81.25,
  "aip2017": 38.89,
  "aip2015": 0,
  "aip2015insitu": 39.39,
  "aipPromedio": 40.04666667
 },
 {
  "id_dep": 14,
  "departamento": "Quiché",
  "id_municipal": 1404,
  "municipio": "Zacualpa",
  "aip2019": 5.26,
  "aip2017": 35,
  "aip2015": 0,
  "aip2015insitu": 50,
  "aipPromedio": 13.42
 },
 {
  "id_dep": 11,
  "departamento": "Retalhuleu",
  "id_municipal": 1107,
  "municipio": "Champerico",
  "aip2019": 20,
  "aip2017": 0,
  "aipPromedio": 10
 },
 {
  "id_dep": 11,
  "departamento": "Retalhuleu",
  "id_municipal": 1109,
  "municipio": "El Asintal",
  "aip2019": 0,
  "aip2017": 0,
  "aip2015": 0,
  "aip2015insitu": 37.04,
  "aipPromedio": 0
 },
 {
  "id_dep": 11,
  "departamento": "Retalhuleu",
  "id_municipal": 1108,
  "municipio": "Nuevo San Carlos",
  "aip2019": 44.74,
  "aip2017": 0,
  "aip2015": 0,
  "aip2015insitu": 76.85,
  "aipPromedio": 14.91333333
 },
 {
  "id_dep": 11,
  "departamento": "Retalhuleu",
  "id_municipal": 1101,
  "municipio": "Retalhuleu",
  "aip2019": 23.08,
  "aip2017": 20,
  "aipPromedio": 21.54
 },
 {
  "id_dep": 11,
  "departamento": "Retalhuleu",
  "id_municipal": 1106,
  "municipio": "San Andrés Villa Seca",
  "aip2019": 2.5,
  "aip2017": 0,
  "aip2015": 0,
  "aip2015insitu": 66.86,
  "aipPromedio": 0.8333333333
 },
 {
  "id_dep": 11,
  "departamento": "Retalhuleu",
  "id_municipal": 1105,
  "municipio": "San Felipe Retalhuleu",
  "aip2019": 15,
  "aip2017": 0,
  "aipPromedio": 7.5
 },
 {
  "id_dep": 11,
  "departamento": "Retalhuleu",
  "id_municipal": 1104,
  "municipio": "San Martín Zapotitlán",
  "aip2019": 0,
  "aip2017": 0,
  "aipPromedio": 0
 },
 {
  "id_dep": 11,
  "departamento": "Retalhuleu",
  "id_municipal": 1102,
  "municipio": "San Sebastián",
  "aip2019": 47.5,
  "aip2017": 0,
  "aip2015": 0,
  "aip2015insitu": 82.18,
  "aipPromedio": 15.83333333
 },
 {
  "id_dep": 11,
  "departamento": "Retalhuleu",
  "id_municipal": 1103,
  "municipio": "Santa Cruz Muluá",
  "aip2019": 46.25,
  "aip2017": 0,
  "aipPromedio": 23.125
 },
 {
  "id_dep": 3,
  "departamento": "Sacatepéquez",
  "id_municipal": 301,
  "municipio": "Antigua Guatemala",
  "aip2019": 56.25,
  "aip2017": 64.29,
  "aipPromedio": 60.27
 },
 {
  "id_dep": 3,
  "departamento": "Sacatepéquez",
  "id_municipal": 312,
  "municipio": "Ciudad Vieja",
  "aip2019": 41.03,
  "aip2017": 0,
  "aipPromedio": 20.515
 },
 {
  "id_dep": 3,
  "departamento": "Sacatepéquez",
  "id_municipal": 302,
  "municipio": "Jocotenango",
  "aip2019": 30,
  "aip2017": 25,
  "aip2015": 0,
  "aip2015insitu": 94.1,
  "aipPromedio": 18.33333333
 },
 {
  "id_dep": 3,
  "departamento": "Sacatepéquez",
  "id_municipal": 310,
  "municipio": "Magdalena Milpas Altas",
  "aip2019": 0,
  "aip2017": 0,
  "aip2015": 0,
  "aip2015insitu": 87.01,
  "aipPromedio": 0
 },
 {
  "id_dep": 3,
  "departamento": "Sacatepéquez",
  "id_municipal": 303,
  "municipio": "Pastores",
  "aip2019": 76.25,
  "aip2017": 50,
  "aip2015": 0,
  "aip2015insitu": 92.03,
  "aipPromedio": 42.08333333
 },
 {
  "id_dep": 3,
  "departamento": "Sacatepéquez",
  "id_municipal": 315,
  "municipio": "San Antonio Aguas Calientes",
  "aip2019": 7.5,
  "aip2017": 0,
  "aip2015": 0,
  "aip2015insitu": 85.27,
  "aipPromedio": 2.5
 },
 {
  "id_dep": 3,
  "departamento": "Sacatepéquez",
  "id_municipal": 307,
  "municipio": "San Bartolomé Milpas Altas",
  "aip2019": 0,
  "aip2017": 55.1,
  "aipPromedio": 27.55
 },
 {
  "id_dep": 3,
  "departamento": "Sacatepéquez",
  "id_municipal": 314,
  "municipio": "Alotenango",
  "aip2019": 37.5,
  "aip2017": 25,
  "aip2015": 0,
  "aip2015insitu": 87.49,
  "aipPromedio": 20.83333333
 },
 {
  "id_dep": 3,
  "departamento": "Sacatepéquez",
  "id_municipal": 308,
  "municipio": "San Lucas Sacatepéquez",
  "aip2019": 72.97,
  "aip2017": 0,
  "aipPromedio": 36.485
 },
 {
  "id_dep": 3,
  "departamento": "Sacatepéquez",
  "id_municipal": 313,
  "municipio": "San Miguel Dueñas",
  "aip2019": 5.13,
  "aip2017": 0,
  "aip2015": 11.25,
  "aip2015insitu": 82.96,
  "aipPromedio": 5.46
 },
 {
  "id_dep": 3,
  "departamento": "Sacatepéquez",
  "id_municipal": 316,
  "municipio": "Santa Catarina Barahona",
  "aip2019": 52.86,
  "aip2017": 20,
  "aip2015": 17.5,
  "aip2015insitu": 85.39,
  "aipPromedio": 30.12
 },
 {
  "id_dep": 3,
  "departamento": "Sacatepéquez",
  "id_municipal": 309,
  "municipio": "Santa Lucía Milpas Altas",
  "aip2019": 0,
  "aip2017": 55.56,
  "aip2015": 28.04,
  "aip2015insitu": 91.4,
  "aipPromedio": 27.86666667
 },
 {
  "id_dep": 3,
  "departamento": "Sacatepéquez",
  "id_municipal": 311,
  "municipio": "Santa María de Jesús",
  "aip2019": 0,
  "aip2017": 0,
  "aip2015": 0,
  "aip2015insitu": 85.93,
  "aipPromedio": 0
 },
 {
  "id_dep": 3,
  "departamento": "Sacatepéquez",
  "id_municipal": 306,
  "municipio": "Santiago Sacatepéquez",
  "aip2019": 97.5,
  "aip2017": 10,
  "aipPromedio": 53.75
 },
 {
  "id_dep": 3,
  "departamento": "Sacatepéquez",
  "id_municipal": 305,
  "municipio": "Santo Domingo Xenacoj",
  "aip2019": 0,
  "aip2017": 17.86,
  "aipPromedio": 8.93
 },
 {
  "id_dep": 3,
  "departamento": "Sacatepéquez",
  "id_municipal": 304,
  "municipio": "Sumpango",
  "aip2019": 91.25,
  "aip2017": 50,
  "aip2015": 0,
  "aip2015insitu": 87.07,
  "aipPromedio": 47.08333333
 },
 {
  "id_dep": 12,
  "departamento": "San Marcos",
  "id_municipal": 1217,
  "municipio": "Ayutla",
  "aip2019": 0,
  "aip2017": 25,
  "aip2015": 0,
  "aip2015insitu": 87.16,
  "aipPromedio": 8.333333333
 },
 {
  "id_dep": 12,
  "departamento": "San Marcos",
  "id_municipal": 1216,
  "municipio": "Catarina",
  "aip2019": 50,
  "aip2017": 25,
  "aip2015": 0,
  "aip2015insitu": 76.88,
  "aipPromedio": 25
 },
 {
  "id_dep": 12,
  "departamento": "San Marcos",
  "id_municipal": 1204,
  "municipio": "Comitancillo",
  "aip2019": 37.5,
  "aip2017": 0,
  "aip2015": 0,
  "aip2015insitu": 44.72,
  "aipPromedio": 12.5
 },
 {
  "id_dep": 12,
  "departamento": "San Marcos",
  "id_municipal": 1206,
  "municipio": "Concepción Tutuapa",
  "aip2019": 23.68,
  "aip2017": 15,
  "aip2015": 0,
  "aip2015insitu": 49.56,
  "aipPromedio": 12.89333333
 },
 {
  "id_dep": 12,
  "departamento": "San Marcos",
  "id_municipal": 1220,
  "municipio": "El Quetzal",
  "aip2019": 22.73,
  "aip2017": 35,
  "aip2015": 0,
  "aip2015insitu": 47.11,
  "aipPromedio": 19.24333333
 },
 {
  "id_dep": 12,
  "departamento": "San Marcos",
  "id_municipal": 1213,
  "municipio": "El Tumbador",
  "aip2019": 5,
  "aip2017": 0,
  "aip2015": 10,
  "aip2015insitu": 76.82,
  "aipPromedio": 5
 },
 {
  "id_dep": 12,
  "departamento": "San Marcos",
  "id_municipal": 1227,
  "municipio": "Esquipulas Palo Gordo",
  "aip2019": 0,
  "aip2017": 0,
  "aip2015": 0,
  "aip2015insitu": 87.19,
  "aipPromedio": 0
 },
 {
  "id_dep": 12,
  "departamento": "San Marcos",
  "id_municipal": 1223,
  "municipio": "Ixchiguán",
  "aip2019": 61.25000000000001,
  "aip2017": 5,
  "aip2015": 0,
  "aip2015insitu": 50.28,
  "aipPromedio": 22.08333333
 },
 {
  "id_dep": 12,
  "departamento": "San Marcos",
  "id_municipal": 1230,
  "municipio": "La Blanca",
  "aip2019": 27.63,
  "aip2017": 0,
  "aip2015": 0,
  "aip2015insitu": 16.56,
  "aipPromedio": 9.21
 },
 {
  "id_dep": 12,
  "departamento": "San Marcos",
  "id_municipal": 1221,
  "municipio": "La Reforma",
  "aip2019": 33.33,
  "aip2017": 55.56,
  "aipPromedio": 44.445
 },
 {
  "id_dep": 12,
  "departamento": "San Marcos",
  "id_municipal": 1215,
  "municipio": "Malacatán",
  "aip2019": 13.750000000000002,
  "aip2017": 0,
  "aipPromedio": 6.875
 },
 {
  "id_dep": 12,
  "departamento": "San Marcos",
  "id_municipal": 1212,
  "municipio": "Nuevo Progreso",
  "aip2019": 64.47,
  "aip2017": 0,
  "aip2015": 0,
  "aip2015insitu": 42.82,
  "aipPromedio": 21.49
 },
 {
  "id_dep": 12,
  "departamento": "San Marcos",
  "id_municipal": 1218,
  "municipio": "Ocós",
  "aip2019": 13.16,
  "aip2017": 35,
  "aipPromedio": 24.08
 },
 {
  "id_dep": 12,
  "departamento": "San Marcos",
  "id_municipal": 1222,
  "municipio": "Pajapita",
  "aip2019": 13.16,
  "aip2017": 5,
  "aipPromedio": 9.08
 },
 {
  "id_dep": 12,
  "departamento": "San Marcos",
  "id_municipal": 1228,
  "municipio": "Río Blanco",
  "aip2019": 0,
  "aip2017": 20,
  "aip2015": 0,
  "aip2015insitu": 38.33,
  "aipPromedio": 6.666666667
 },
 {
  "id_dep": 12,
  "departamento": "San Marcos",
  "id_municipal": 1203,
  "municipio": "San Antonio Sacatepéquez",
  "aip2019": 26.32,
  "aip2017": 60,
  "aip2015": 0,
  "aip2015insitu": 83.95,
  "aipPromedio": 28.77333333
 },
 {
  "id_dep": 12,
  "departamento": "San Marcos",
  "id_municipal": 1225,
  "municipio": "San Cristóbal Cucho",
  "aip2019": 87.5,
  "aip2017": 5,
  "aipPromedio": 46.25
 },
 {
  "id_dep": 12,
  "departamento": "San Marcos",
  "id_municipal": 1214,
  "municipio": "El Rodeo",
  "aip2019": 5,
  "aip2017": 0,
  "aip2015": 0,
  "aip2015insitu": 0,
  "aipPromedio": 1.666666667
 },
 {
  "id_dep": 12,
  "departamento": "San Marcos",
  "id_municipal": 1224,
  "municipio": "San José Ojetenam",
  "aip2019": 0,
  "aip2017": 0,
  "aipPromedio": 0
 },
 {
  "id_dep": 12,
  "departamento": "San Marcos",
  "id_municipal": 1229,
  "municipio": "San Lorenzo",
  "aip2019": 5,
  "aip2017": 0,
  "aipPromedio": 2.5
 },
 {
  "id_dep": 12,
  "departamento": "San Marcos",
  "id_municipal": 1201,
  "municipio": "San Marcos",
  "aip2019": 37.5,
  "aip2017": 30,
  "aipPromedio": 33.75
 },
 {
  "id_dep": 12,
  "departamento": "San Marcos",
  "id_municipal": 1205,
  "municipio": "San Miguel Ixtahuacán",
  "aip2019": 26.25,
  "aip2017": 5,
  "aip2015": 5,
  "aip2015insitu": 92.54,
  "aipPromedio": 12.08333333
 },
 {
  "id_dep": 12,
  "departamento": "San Marcos",
  "id_municipal": 1219,
  "municipio": "San Pablo",
  "aip2019": 0,
  "aip2017": 0,
  "aip2015": 0,
  "aip2015insitu": 57.78,
  "aipPromedio": 0
 },
 {
  "id_dep": 12,
  "departamento": "San Marcos",
  "id_municipal": 1202,
  "municipio": "San Pedro Sacatepéquez",
  "aip2019": 9.21,
  "aip2017": 0,
  "aip2015": 26.18,
  "aip2015insitu": 53.49,
  "aipPromedio": 11.79666667
 },
 {
  "id_dep": 12,
  "departamento": "San Marcos",
  "id_municipal": 1211,
  "municipio": "San Rafael Pie de la Cuesta",
  "aip2019": 0,
  "aip2017": 0,
  "aip2015": 0,
  "aip2015insitu": 17.78,
  "aipPromedio": 0
 },
 {
  "id_dep": 12,
  "departamento": "San Marcos",
  "id_municipal": 1208,
  "municipio": "Sibinal",
  "aip2019": 31.58,
  "aip2017": 0,
  "aip2015": 0,
  "aip2015insitu": 25.48,
  "aipPromedio": 10.52666667
 },
 {
  "id_dep": 12,
  "departamento": "San Marcos",
  "id_municipal": 1226,
  "municipio": "Sipacapa",
  "aip2019": 20,
  "aip2017": 0,
  "aip2015": 0,
  "aip2015insitu": 0,
  "aipPromedio": 6.666666667
 },
 {
  "id_dep": 12,
  "departamento": "San Marcos",
  "id_municipal": 1207,
  "municipio": "Tacaná",
  "aip2019": 73.68,
  "aip2017": 35,
  "aip2015": 0,
  "aip2015insitu": 70.56,
  "aipPromedio": 36.22666667
 },
 {
  "id_dep": 12,
  "departamento": "San Marcos",
  "id_municipal": 1209,
  "municipio": "Tajumulco",
  "aip2019": 5,
  "aip2017": 0,
  "aip2015": 0,
  "aip2015insitu": 6.67,
  "aipPromedio": 1.666666667
 },
 {
  "id_dep": 12,
  "departamento": "San Marcos",
  "id_municipal": 1210,
  "municipio": "Tejutla",
  "aip2019": 11.25,
  "aip2017": 25,
  "aip2015": 0,
  "aip2015insitu": 35.56,
  "aipPromedio": 12.08333333
 },
 {
  "id_dep": 6,
  "departamento": "Santa Rosa",
  "id_municipal": 602,
  "municipio": "Barberena",
  "aip2019": 68.97,
  "aip2017": 0,
  "aip2015": 0,
  "aip2015insitu": 84.91,
  "aipPromedio": 22.99
 },
 {
  "id_dep": 6,
  "departamento": "Santa Rosa",
  "id_municipal": 604,
  "municipio": "Casillas",
  "aip2019": 48.65,
  "aip2017": 0,
  "aip2015": 0,
  "aip2015insitu": 79.12,
  "aipPromedio": 16.21666667
 },
 {
  "id_dep": 6,
  "departamento": "Santa Rosa",
  "id_municipal": 608,
  "municipio": "Chiquimulilla",
  "aip2019": 36.67,
  "aip2017": 0,
  "aipPromedio": 18.335
 },
 {
  "id_dep": 6,
  "departamento": "Santa Rosa",
  "id_municipal": 601,
  "municipio": "Cuilapa",
  "aip2019": 66,
  "aip2017": 0,
  "aip2015": 0,
  "aip2015insitu": 36.82,
  "aipPromedio": 22
 },
 {
  "id_dep": 6,
  "departamento": "Santa Rosa",
  "id_municipal": 611,
  "municipio": "Guazacapán",
  "aip2019": 22.06,
  "aip2017": 0,
  "aipPromedio": 11.03
 },
 {
  "id_dep": 6,
  "departamento": "Santa Rosa",
  "id_municipal": 614,
  "municipio": "Nueva Santa Rosa",
  "aip2019": 59.09,
  "aip2017": 30,
  "aip2015": 33.15,
  "aip2015insitu": 71.07,
  "aipPromedio": 40.74666667
 },
 {
  "id_dep": 6,
  "departamento": "Santa Rosa",
  "id_municipal": 606,
  "municipio": "Oratorio",
  "aip2019": 66.18,
  "aip2017": 0,
  "aipPromedio": 33.09
 },
 {
  "id_dep": 6,
  "departamento": "Santa Rosa",
  "id_municipal": 613,
  "municipio": "Pueblo Nuevo Viñas",
  "aip2019": 20,
  "aip2017": 43.75,
  "aip2015": 0,
  "aip2015insitu": 13.33,
  "aipPromedio": 21.25
 },
 {
  "id_dep": 6,
  "departamento": "Santa Rosa",
  "id_municipal": 607,
  "municipio": "San Juan Tecuaco",
  "aip2019": 40,
  "aip2017": 0,
  "aipPromedio": 20
 },
 {
  "id_dep": 6,
  "departamento": "Santa Rosa",
  "id_municipal": 605,
  "municipio": "San Rafael Las Flores",
  "aip2019": 41.03,
  "aip2017": 22.72,
  "aipPromedio": 31.875
 },
 {
  "id_dep": 6,
  "departamento": "Santa Rosa",
  "id_municipal": 612,
  "municipio": "Santa Cruz Naranjo",
  "aip2019": 40,
  "aip2017": 0,
  "aip2015": 2.5,
  "aip2015insitu": 72.58,
  "aipPromedio": 14.16666667
 },
 {
  "id_dep": 6,
  "departamento": "Santa Rosa",
  "id_municipal": 610,
  "municipio": "Santa María Ixhuatán",
  "aip2019": 52.78,
  "aip2017": 0,
  "aip2015": 2.5,
  "aip2015insitu": 72.79,
  "aipPromedio": 18.42666667
 },
 {
  "id_dep": 6,
  "departamento": "Santa Rosa",
  "id_municipal": 603,
  "municipio": "Santa Rosa de Lima",
  "aip2019": 62.5,
  "aip2017": 18.18,
  "aipPromedio": 40.34
 },
 {
  "id_dep": 6,
  "departamento": "Santa Rosa",
  "id_municipal": 609,
  "municipio": "Taxisco",
  "aip2019": 35.29,
  "aip2017": 0,
  "aipPromedio": 17.645
 },
 {
  "id_dep": 7,
  "departamento": "Sololá",
  "id_municipal": 708,
  "municipio": "Concepción",
  "aip2019": 13.16,
  "aip2017": 0,
  "aip2015": 0,
  "aip2015insitu": 10.26,
  "aipPromedio": 4.386666667
 },
 {
  "id_dep": 7,
  "departamento": "Sololá",
  "id_municipal": 705,
  "municipio": "Nahualá",
  "aip2019": 41.89,
  "aip2017": 40,
  "aip2015": 44.62,
  "aip2015insitu": 62.5,
  "aipPromedio": 42.17
 },
 {
  "id_dep": 7,
  "departamento": "Sololá",
  "id_municipal": 710,
  "municipio": "Panajachel",
  "aip2019": 10.81,
  "aip2017": 0,
  "aipPromedio": 5.405
 },
 {
  "id_dep": 7,
  "departamento": "Sololá",
  "id_municipal": 709,
  "municipio": "San Andrés Semetabaj",
  "aip2019": 0,
  "aip2017": 0,
  "aipPromedio": 0
 },
 {
  "id_dep": 7,
  "departamento": "Sololá",
  "id_municipal": 712,
  "municipio": "San Antonio Palopó",
  "aip2019": 15.79,
  "aip2017": 0,
  "aipPromedio": 7.895
 },
 {
  "id_dep": 7,
  "departamento": "Sololá",
  "id_municipal": 702,
  "municipio": "San José Chacayá",
  "aip2019": 7.5,
  "aip2017": 0,
  "aipPromedio": 3.75
 },
 {
  "id_dep": 7,
  "departamento": "Sololá",
  "id_municipal": 717,
  "municipio": "San Juan La Laguna",
  "aip2019": 0,
  "aip2017": 0,
  "aip2015": 0,
  "aip2015insitu": 78.13,
  "aipPromedio": 0
 },
 {
  "id_dep": 7,
  "departamento": "Sololá",
  "id_municipal": 713,
  "municipio": "San Lucas Tolimán",
  "aip2019": 32.43,
  "aip2017": 5,
  "aip2015": 0,
  "aip2015insitu": 46.67,
  "aipPromedio": 12.47666667
 },
 {
  "id_dep": 7,
  "departamento": "Sololá",
  "id_municipal": 716,
  "municipio": "San Marcos La Laguna",
  "aip2019": 71.61999999999999,
  "aip2017": 0,
  "aipPromedio": 35.81
 },
 {
  "id_dep": 7,
  "departamento": "Sololá",
  "id_municipal": 715,
  "municipio": "San Pablo La Laguna",
  "aip2019": 11.25,
  "aip2017": 0,
  "aip2015": 0,
  "aip2015insitu": 76.39,
  "aipPromedio": 3.75
 },
 {
  "id_dep": 7,
  "departamento": "Sololá",
  "id_municipal": 718,
  "municipio": "San Pedro La Laguna",
  "aip2019": 52.559999999999995,
  "aip2017": 30,
  "aip2015": 27.19,
  "aip2015insitu": 50.83,
  "aipPromedio": 36.58333333
 },
 {
  "id_dep": 7,
  "departamento": "Sololá",
  "id_municipal": 706,
  "municipio": "Santa Catarina Ixtahuacán",
  "aip2019": 0,
  "aip2017": 26.77,
  "aipPromedio": 13.385
 },
 {
  "id_dep": 7,
  "departamento": "Sololá",
  "id_municipal": 711,
  "municipio": "Santa Catarina Palopó",
  "aip2019": 7.89,
  "aip2017": 0,
  "aipPromedio": 3.945
 },
 {
  "id_dep": 7,
  "departamento": "Sololá",
  "id_municipal": 707,
  "municipio": "Santa Clara La Laguna",
  "aip2019": 55.13,
  "aip2017": 0,
  "aip2015": 0,
  "aip2015insitu": 88.64,
  "aipPromedio": 18.37666667
 },
 {
  "id_dep": 7,
  "departamento": "Sololá",
  "id_municipal": 714,
  "municipio": "Santa Cruz La Laguna",
  "aip2019": 0,
  "aip2017": 0,
  "aipPromedio": 0
 },
 {
  "id_dep": 7,
  "departamento": "Sololá",
  "id_municipal": 704,
  "municipio": "Santa Lucía Utatlán",
  "aip2019": 7.89,
  "aip2017": 10,
  "aipPromedio": 8.945
 },
 {
  "id_dep": 7,
  "departamento": "Sololá",
  "id_municipal": 703,
  "municipio": "Santa María Visitación",
  "aip2019": 77.78,
  "aip2017": 30,
  "aip2015": 0,
  "aip2015insitu": 88.64,
  "aipPromedio": 35.92666667
 },
 {
  "id_dep": 7,
  "departamento": "Sololá",
  "id_municipal": 719,
  "municipio": "Santiago Atitlán",
  "aip2019": 0,
  "aip2017": 40,
  "aip2015": 5,
  "aip2015insitu": 38.1,
  "aipPromedio": 15
 },
 {
  "id_dep": 7,
  "departamento": "Sololá",
  "id_municipal": 701,
  "municipio": "Sololá",
  "aip2019": 17.5,
  "aip2017": 0,
  "aipPromedio": 8.75
 },
 {
  "id_dep": 10,
  "departamento": "Suchitepéquez",
  "id_municipal": 1013,
  "municipio": "Chicacao",
  "aip2019": 40.79,
  "aip2017": 0,
  "aipPromedio": 20.395
 },
 {
  "id_dep": 10,
  "departamento": "Suchitepéquez",
  "id_municipal": 1002,
  "municipio": "Cuyotenango",
  "aip2019": 75,
  "aip2017": 0,
  "aipPromedio": 37.5
 },
 {
  "id_dep": 10,
  "departamento": "Suchitepéquez",
  "id_municipal": 1001,
  "municipio": "Mazatenango",
  "aip2019": 34.72,
  "aip2017": 0,
  "aipPromedio": 17.36
 },
 {
  "id_dep": 10,
  "departamento": "Suchitepéquez",
  "id_municipal": 1014,
  "municipio": "Patulul",
  "aip2019": 10.53,
  "aip2017": 0,
  "aip2015": 0,
  "aip2015insitu": 12.5,
  "aipPromedio": 3.51
 },
 {
  "id_dep": 10,
  "departamento": "Suchitepéquez",
  "id_municipal": 1019,
  "municipio": "Pueblo Nuevo",
  "aip2019": 42.11,
  "aip2017": 0,
  "aip2015": 0,
  "aip2015insitu": 24.69,
  "aipPromedio": 14.03666667
 },
 {
  "id_dep": 10,
  "departamento": "Suchitepéquez",
  "id_municipal": 1020,
  "municipio": "Río Bravo",
  "aip2019": 23.68,
  "aip2017": 35,
  "aipPromedio": 29.34
 },
 {
  "id_dep": 10,
  "departamento": "Suchitepéquez",
  "id_municipal": 1008,
  "municipio": "Samayac",
  "aip2019": 34.21,
  "aip2017": 10,
  "aipPromedio": 22.105
 },
 {
  "id_dep": 10,
  "departamento": "Suchitepéquez",
  "id_municipal": 1010,
  "municipio": "San Antonio Suchitepéquez",
  "aip2019": 68.42,
  "aip2017": 21.59,
  "aipPromedio": 45.005
 },
 {
  "id_dep": 10,
  "departamento": "Suchitepéquez",
  "id_municipal": 1004,
  "municipio": "San Bernardino",
  "aip2019": 0,
  "aip2017": 0,
  "aipPromedio": 0
 },
 {
  "id_dep": 10,
  "departamento": "Suchitepéquez",
  "id_municipal": 1003,
  "municipio": "San Francisco Zapotitlán",
  "aip2019": 22.97,
  "aip2017": 0,
  "aipPromedio": 11.485
 },
 {
  "id_dep": 10,
  "departamento": "Suchitepéquez",
  "id_municipal": 1012,
  "municipio": "San Gabriel",
  "aip2019": 52.629999999999995,
  "aip2017": 0,
  "aip2015": 0,
  "aip2015insitu": 64.45,
  "aipPromedio": 17.54333333
 },
 {
  "id_dep": 10,
  "departamento": "Suchitepéquez",
  "id_municipal": 1005,
  "municipio": "San José El Ídolo",
  "aip2019": 85.53,
  "aip2017": 5,
  "aip2015": 0,
  "aip2015insitu": 18.53,
  "aipPromedio": 30.17666667
 },
 {
  "id_dep": 10,
  "departamento": "Suchitepéquez",
  "id_municipal": 1021,
  "municipio": "San José La Máquina",
  "aip2019": 92.11,
  "aip2017": 20,
  "aip2015": 0,
  "aip2015insitu": 30.51,
  "aipPromedio": 37.37
 },
 {
  "id_dep": 10,
  "departamento": "Suchitepéquez",
  "id_municipal": 1016,
  "municipio": "San Juan Bautista",
  "aip2019": 76.32,
  "aip2017": 56.25,
  "aip2015": 15.2,
  "aip2015insitu": 65.23,
  "aipPromedio": 49.25666667
 },
 {
  "id_dep": 10,
  "departamento": "Suchitepéquez",
  "id_municipal": 1007,
  "municipio": "San Lorenzo",
  "aip2019": 14.47,
  "aip2017": 0,
  "aip2015": 0,
  "aip2015insitu": 0,
  "aipPromedio": 4.823333333
 },
 {
  "id_dep": 10,
  "departamento": "Suchitepéquez",
  "id_municipal": 1011,
  "municipio": "San Miguel Panán",
  "aip2019": 9.46,
  "aip2017": 0,
  "aip2015": 0,
  "aip2015insitu": 18.52,
  "aipPromedio": 3.153333333
 },
 {
  "id_dep": 10,
  "departamento": "Suchitepéquez",
  "id_municipal": 1009,
  "municipio": "San Pablo Jocopilas",
  "aip2019": 8.33,
  "aip2017": 0,
  "aipPromedio": 4.165
 },
 {
  "id_dep": 10,
  "departamento": "Suchitepéquez",
  "id_municipal": 1015,
  "municipio": "Santa Bárbara",
  "aip2019": 76.23,
  "aip2017": 25,
  "aip2015": 0,
  "aip2015insitu": 70.75,
  "aipPromedio": 33.74333333
 },
 {
  "id_dep": 10,
  "departamento": "Suchitepéquez",
  "id_municipal": 1006,
  "municipio": "Santo Domingo Suchitepéquez",
  "aip2019": 6.94,
  "aip2017": 0,
  "aip2015": 0,
  "aip2015insitu": 57.65,
  "aipPromedio": 2.313333333
 },
 {
  "id_dep": 10,
  "departamento": "Suchitepéquez",
  "id_municipal": 1017,
  "municipio": "Santo Tomas La Unión",
  "aip2019": 78.95,
  "aip2017": 0,
  "aip2015": 0,
  "aip2015insitu": 56.54,
  "aipPromedio": 26.31666667
 },
 {
  "id_dep": 10,
  "departamento": "Suchitepéquez",
  "id_municipal": 1018,
  "municipio": "Zunilito",
  "aip2019": 76.32,
  "aip2017": 0,
  "aip2015": 0,
  "aip2015insitu": 88.7,
  "aipPromedio": 25.44
 },
 {
  "id_dep": 8,
  "departamento": "Totonicapán",
  "id_municipal": 805,
  "municipio": "Momostenango",
  "aip2019": 93.94,
  "aip2017": 20,
  "aip2015": 0,
  "aip2015insitu": 93.18,
  "aipPromedio": 37.98
 },
 {
  "id_dep": 8,
  "departamento": "Totonicapán",
  "id_municipal": 804,
  "municipio": "San Andrés Xecul",
  "aip2019": 87.5,
  "aip2017": 0,
  "aipPromedio": 43.75
 },
 {
  "id_dep": 8,
  "departamento": "Totonicapán",
  "id_municipal": 808,
  "municipio": "San Bartolo Aguas Calientes",
  "aip2019": 93.06,
  "aip2017": 0,
  "aipPromedio": 46.53
 },
 {
  "id_dep": 8,
  "departamento": "Totonicapán",
  "id_municipal": 802,
  "municipio": "San Cristóbal Totonicapán",
  "aip2019": 96.77,
  "aip2017": 27.78,
  "aipPromedio": 62.275
 },
 {
  "id_dep": 8,
  "departamento": "Totonicapán",
  "id_municipal": 803,
  "municipio": "San Francisco El Alto",
  "aip2019": 84.85000000000001,
  "aip2017": 20,
  "aip2015": 0,
  "aip2015insitu": 91.09,
  "aipPromedio": 34.95
 },
 {
  "id_dep": 8,
  "departamento": "Totonicapán",
  "id_municipal": 807,
  "municipio": "Santa Lucía La Reforma",
  "aip2019": 53.33,
  "aip2017": 0,
  "aip2015": 0,
  "aip2015insitu": 95.45,
  "aipPromedio": 17.77666667
 },
 {
  "id_dep": 8,
  "departamento": "Totonicapán",
  "id_municipal": 806,
  "municipio": "Santa María Chiquimula",
  "aip2019": 78.57,
  "aip2017": 37.5,
  "aipPromedio": 58.035
 },
 {
  "id_dep": 8,
  "departamento": "Totonicapán",
  "id_municipal": 801,
  "municipio": "Totonicapán",
  "aip2019": 95.71,
  "aip2017": 0,
  "aipPromedio": 47.855
 },
 {
  "id_dep": 19,
  "departamento": "Zacapa",
  "id_municipal": 1907,
  "municipio": "Cabañas",
  "aip2019": 75.76,
  "aip2017": 33.33,
  "aipPromedio": 54.545
 },
 {
  "id_dep": 19,
  "departamento": "Zacapa",
  "id_municipal": 1902,
  "municipio": "Estanzuela",
  "aip2019": 0,
  "aip2017": 0,
  "aipPromedio": 0
 },
 {
  "id_dep": 19,
  "departamento": "Zacapa",
  "id_municipal": 1904,
  "municipio": "Gualán",
  "aip2019": 70.97,
  "aip2017": 9.09,
  "aipPromedio": 40.03
 },
 {
  "id_dep": 19,
  "departamento": "Zacapa",
  "id_municipal": 1910,
  "municipio": "Huité",
  "aip2019": 66.67,
  "aip2017": 9.09,
  "aipPromedio": 37.88
 },
 {
  "id_dep": 19,
  "departamento": "Zacapa",
  "id_municipal": 1909,
  "municipio": "La Unión",
  "aip2019": 74.07000000000001,
  "aip2017": 0,
  "aipPromedio": 37.035
 },
 {
  "id_dep": 19,
  "departamento": "Zacapa",
  "id_municipal": 1903,
  "municipio": "Río Hondo",
  "aip2019": 0,
  "aip2017": 0,
  "aipPromedio": 0
 },
 {
  "id_dep": 19,
  "departamento": "Zacapa",
  "id_municipal": 1908,
  "municipio": "San Diego",
  "aip2019": 0,
  "aip2017": 0,
  "aipPromedio": 0
 },
 {
  "id_dep": 19,
  "departamento": "Zacapa",
  "id_municipal": 1911,
  "municipio": "San Jorge",
  "aip2019": 27.78,
  "aip2017": 0,
  "aipPromedio": 13.89
 },
 {
  "id_dep": 19,
  "departamento": "Zacapa",
  "id_municipal": 1905,
  "municipio": "Teculután",
  "aip2019": 76.55999999999999,
  "aip2017": 0,
  "aipPromedio": 38.28
 },
 {
  "id_dep": 19,
  "departamento": "Zacapa",
  "id_municipal": 1906,
  "municipio": "Usumatlán",
  "aip2019": 82.26,
  "aip2017": 0,
  "aipPromedio": 41.13
 },
 {
  "id_dep": 19,
  "departamento": "Zacapa",
  "id_municipal": 1901,
  "municipio": "Zacapa",
  "aip2019": 35.53,
  "aip2017": 0,
  "aipPromedio": 17.765
 }
]